grapl_graph_descriptions/__init__.py
grapl_graph_descriptions/graph_description_pb2.py
grapl_graph_descriptions-1.0.5.dist-info/METADATA
grapl_graph_descriptions-1.0.5.dist-info/WHEEL
grapl_graph_descriptions-1.0.5.dist-info/top_level.txt
grapl_graph_descriptions-1.0.5.dist-info/RECORD
